LICENSE
MANIFEST.in
README.md
setup.cfg
setup.py
docs/conf.py
src/pupper/__init__.py
src/pupper/cli.py
src/pupper.egg-info/PKG-INFO
src/pupper.egg-info/SOURCES.txt
src/pupper.egg-info/dependency_links.txt
src/pupper.egg-info/entry_points.txt
src/pupper.egg-info/not-zip-safe
src/pupper.egg-info/requires.txt
src/pupper.egg-info/top_level.txt
test/test_pupper.py