Metadata-Version: 1.1
Name: pupper
Version: 0.0.1
Summary: Pupper is a utility to manage all your python cli utils!
Home-page: https://github.com/sixninetynine/pupper
Author: Loren M. Carvalho
Author-email: me@loren.pizza
License: MIT license
Keywords: pupper
Platform: UNKNOWN
Classifier: Development Status :: 2 - Pre-Alpha
Classifier: Intended Audience :: Developers
Classifier: License :: OSI Approved :: MIT License
Classifier: Natural Language :: English
Classifier: Programming Language :: Python :: 2
Classifier: Programming Language :: Python :: 2.6
Classifier: Programming Language :: Python :: 2.7
Classifier: Programming Language :: Python :: 3
Classifier: Programming Language :: Python :: 3.3
Classifier: Programming Language :: Python :: 3.4
Classifier: Programming Language :: Python :: 3.5
